packcircles/__init__.py
packcircles/packcircles.py
packcircles-0.14.dist-info/LICENSE
packcircles-0.14.dist-info/METADATA
packcircles-0.14.dist-info/WHEEL
packcircles-0.14.dist-info/top_level.txt
packcircles-0.14.dist-info/RECORD
