Metadata-Version: 2.1
Name: packcircles
Version: 0.14
Summary: A pure Python implementation of a circle packing algorithm
Home-page: https://github.com/mhtchan/packcircles
Author: mhtchan
Author-email: mhtchan@outlook.com
License: MIT
Platform: UNKNOWN
Requires-Dist: pyllist (>=0.3)
